LICENSE
README.md
pyproject.toml
setup.py
speechbrain/__init__.py
speechbrain/core.py
speechbrain/log-config.yaml
speechbrain/requirements.txt
speechbrain/version.txt
speechbrain/alignment/__init__.py
speechbrain/alignment/aligner.py
speechbrain/alignment/ctc_segmentation.py
speechbrain/dataio/__init__.py
speechbrain/dataio/batch.py
speechbrain/dataio/dataio.py
speechbrain/dataio/dataloader.py
speechbrain/dataio/dataset.py
speechbrain/dataio/encoder.py
speechbrain/dataio/iterators.py
speechbrain/dataio/legacy.py
speechbrain/dataio/preprocess.py
speechbrain/dataio/sampler.py
speechbrain/dataio/wer.py
speechbrain/decoders/__init__.py
speechbrain/decoders/ctc.py
speechbrain/decoders/seq2seq.py
speechbrain/decoders/transducer.py
speechbrain/lm/__init__.py
speechbrain/lm/arpa.py
speechbrain/lm/counting.py
speechbrain/lm/ngram.py
speechbrain/lobes/__init__.py
speechbrain/lobes/augment.py
speechbrain/lobes/beamform_multimic.py
speechbrain/lobes/features.py
speechbrain/lobes/models/CRDNN.py
speechbrain/lobes/models/ContextNet.py
speechbrain/lobes/models/ECAPA_TDNN.py
speechbrain/lobes/models/ESPnetVGG.py
speechbrain/lobes/models/EnhanceResnet.py
speechbrain/lobes/models/HifiGAN.py
speechbrain/lobes/models/MetricGAN.py
speechbrain/lobes/models/MetricGAN_U.py
speechbrain/lobes/models/RNNLM.py
speechbrain/lobes/models/Tacotron2.py
speechbrain/lobes/models/VanillaNN.py
speechbrain/lobes/models/Xvector.py
speechbrain/lobes/models/__init__.py
speechbrain/lobes/models/conv_tasnet.py
speechbrain/lobes/models/convolution.py
speechbrain/lobes/models/dual_path.py
speechbrain/lobes/models/fairseq_wav2vec.py
speechbrain/lobes/models/huggingface_wav2vec.py
speechbrain/lobes/models/resepformer.py
speechbrain/lobes/models/segan_model.py
speechbrain/lobes/models/g2p/__init__.py
speechbrain/lobes/models/g2p/dataio.py
speechbrain/lobes/models/g2p/homograph.py
speechbrain/lobes/models/g2p/model.py
speechbrain/lobes/models/transformer/Conformer.py
speechbrain_geoph9.egg-info/PKG-INFO
speechbrain_geoph9.egg-info/SOURCES.txt
speechbrain_geoph9.egg-info/dependency_links.txt
speechbrain_geoph9.egg-info/requires.txt
speechbrain_geoph9.egg-info/top_level.txt