Metadata-Version: 2.1
Name: speechbrain-geoph9
Version: 0.5.12a0
Summary: All-in-one speech toolkit in pure Python and Pytorch
Home-page: https://speechbrain.github.io/
Author: Mirco Ravanelli & Others
Author-email: speechbrain@gmail.com
Classifier: Programming Language :: Python :: 3
Classifier: License :: OSI Approved :: Apache Software License
Requires-Python: >=3.7
License-File: LICENSE
